{
  "version": "1.1.0",
  "updated": "2026-06-26T12:00:00Z",
  "baseUrl": "https://github.com/aymen-igri/DFCraft_sounds_library/releases/download/v1.0.0",
  "baseImageUrl": "https://raw.githubusercontent.com/aymen-igri/DFCraft_sounds_library/main",
  "description": "A library of ambient sounds for focus and relaxation",

  "categories": [
    {
      "id": "rain",
      "name": "Rain & Thunder",
      "description": "Soothing rain and thunderstorm sounds for deep focus",
      "color": "#4A90E2",
      "tags": ["rain", "thunder", "storm", "water"],
      "coverImage": "https://raw.githubusercontent.com/aymen-igri/DFCraft_sounds_library/main/Images/Rain/rain.jpg",
      "soundCount": 10
    },
    {
      "id": "nature",
      "name": "Nature & Forest",
      "description": "Natural outdoor ambiences and wildlife sounds",
      "color": "#27AE60",
      "tags": ["forest", "ocean", "birds", "nature"],
      "coverImage": "https://raw.githubusercontent.com/aymen-igri/DFCraft_sounds_library/main/Images/Nature%20&%20Forest/forest-512341.jpg",
      "soundCount": 10
    },
    {
      "id": "white-noise",
      "name": "White Noise",
      "description": "Pure focus sounds and noise colors",
      "color": "#95A5A6",
      "tags": ["white", "brown", "pink", "noise"],
      "coverImage": "https://raw.githubusercontent.com/aymen-igri/DFCraft_sounds_library/main/Images/White%20noise/white-noise-403326.jpg",
      "soundCount": 10
    },
    {
      "id": "cafe-indoor",
      "name": "Cafe & Indoor",
      "description": "Cozy cafe and indoor ambient sounds",
      "color": "#E67E22",
      "tags": ["cafe", "coffee", "restaurant", "indoor"],
      "coverImage": "https://raw.githubusercontent.com/aymen-igri/DFCraft_sounds_library/main/Images/Caf%C3%A9%20&%20Indor/cafe-788774.jpg",
      "soundCount": 7
    }
  ],

  "sounds": [
    {
      "id": "heavy-rain-645702",
      "title": "Heavy Rain",
      "category": "rain",
      "duration": 5436,
      "description": "Intense heavy rainfall",
      "file": "https://github.com/aymen-igri/DFCraft_sounds_library/releases/download/v1.0.0/heavy-rain-645702.mp3",
      "coverImage": "https://raw.githubusercontent.com/aymen-igri/DFCraft_sounds_library/main/Images/Rain/heavy-rain-645702.jpg",
      "thumbnail": "https://raw.githubusercontent.com/aymen-igri/DFCraft_sounds_library/main/Images/Rain/heavy-rain-645702.jpg",
      "source": "Freesound",
      "sourceUrl": "https://freesound.org/people/Ambient-X/sounds/645702/",
      "license": "CC0",
      "licenseUrl": "https://creativecommons.org/publicdomain/zero/1.0/",
      "author": "Ambient-X",
      "attribution": null,
      "tags": ["rain", "heavy", "intense", "focus"],
      "featured": false
    },
    {
      "id": "late-may-rain",
      "title": "Late May Rain",
      "category": "rain",
      "duration": 2234,
      "description": "Rain thunder noises",
      "file": "https://github.com/aymen-igri/DFCraft_sounds_library/releases/download/v1.0.0/late-may-rain.mp3",
      "coverImage": null,
      "thumbnail": null,
      "source": null,
      "sourceUrl": null,
      "license": "Unknown",
      "licenseUrl": null,
      "author": "jmorrisoncafe",
      "attribution": null,
      "tags": ["rain", "thunder", "late-may"],
      "featured": false
    },
    {
      "id": "rain-ambience-650969",
      "title": "Rain Ambience",
      "category": "rain",
      "duration": 4614,
      "description": "Gentle rain ambience for relaxation",
      "file": "https://github.com/aymen-igri/DFCraft_sounds_library/releases/download/v1.0.0/rain-ambience-650969.mp3",
      "coverImage": "https://raw.githubusercontent.com/aymen-igri/DFCraft_sounds_library/main/Images/Rain/rain-ambience-650969.jpg",
      "thumbnail": "https://raw.githubusercontent.com/aymen-igri/DFCraft_sounds_library/main/Images/Rain/rain-ambience-650969.jpg",
      "source": "Freesound",
      "sourceUrl": "https://freesound.org/people/Ambient-X/sounds/650969/",
      "license": "CC0",
      "licenseUrl": "https://creativecommons.org/publicdomain/zero/1.0/",
      "author": "Ambient-X",
      "attribution": null,
      "tags": ["rain", "ambient", "gentle", "relaxing"],
      "featured": true
    },
    {
      "id": "rain-heavy-then-light-rolling",
      "title": "Rain Heavy Then Light Rolling",
      "category": "rain",
      "duration": 5200,
      "description": "Rain starting heavy then transitioning to light rolling",
      "file": "https://github.com/aymen-igri/DFCraft_sounds_library/releases/download/v1.0.0/rain-heavy-then-light-rolling.mp3",
      "coverImage": null,
      "thumbnail": null,
      "source": null,
      "sourceUrl": null,
      "license": "Unknown",
      "licenseUrl": null,
      "author": null,
      "attribution": null,
      "tags": ["rain", "heavy", "light", "rolling"],
      "featured": false
    },
    {
      "id": "rain-leaves-681720",
      "title": "Rain on Leaves",
      "category": "rain",
      "duration": 3294,
      "description": "Peaceful rain falling on leaves",
      "file": "https://github.com/aymen-igri/DFCraft_sounds_library/releases/download/v1.0.0/rain-leaves-681720.mp3",
      "coverImage": "https://raw.githubusercontent.com/aymen-igri/DFCraft_sounds_library/main/Images/Rain/rain-leaves-681720.jpg",
      "thumbnail": "https://raw.githubusercontent.com/aymen-igri/DFCraft_sounds_library/main/Images/Rain/rain-leaves-681720.jpg",
      "source": "Freesound",
      "sourceUrl": "https://freesound.org/people/Ambient-X/sounds/681720/",
      "license": "CC0",
      "licenseUrl": "https://creativecommons.org/publicdomain/zero/1.0/",
      "author": "Ambient-X",
      "attribution": null,
      "tags": ["rain", "leaves", "nature", "peaceful"],
      "featured": false
    },
    {
      "id": "rain-under-coat",
      "title": "Rain Under Coat",
      "category": "rain",
      "duration": 4468,
      "description": "Muffled rain sound as if under cover",
      "file": "https://github.com/aymen-igri/DFCraft_sounds_library/releases/download/v1.0.0/rain-under-coat.mp3",
      "coverImage": null,
      "thumbnail": null,
      "source": null,
      "sourceUrl": null,
      "license": "Unknown",
      "licenseUrl": null,
      "author": null,
      "attribution": null,
      "tags": ["rain", "under", "coat", "ambient"],
      "featured": false
    },
    {
      "id": "rain-with-variable-intensity",
      "title": "Rain With Variable Intensity",
      "category": "rain",
      "duration": 2600,
      "description": "Rain with changing intensity levels",
      "file": "https://github.com/aymen-igri/DFCraft_sounds_library/releases/download/v1.0.0/rain-with-variable-intensity.mp3",
      "coverImage": null,
      "thumbnail": null,
      "source": null,
      "sourceUrl": null,
      "license": "Unknown",
      "licenseUrl": null,
      "author": null,
      "attribution": null,
      "tags": ["rain", "variable", "intensity", "dynamic"],
      "featured": false
    },
    {
      "id": "static-277272",
      "title": "Static Noise",
      "category": "rain",
      "duration": 4680,
      "description": "Static noise for blocking distractions",
      "file": "https://github.com/aymen-igri/DFCraft_sounds_library/releases/download/v1.0.0/static-277272.mp3",
      "coverImage": null,
      "thumbnail": null,
      "source": "Freesound",
      "sourceUrl": "https://freesound.org/people/klankbeeld/sounds/277272/",
      "license": "CC BY 4.0",
      "licenseUrl": "https://creativecommons.org/licenses/by/4.0/",
      "author": "klankbeeld",
      "attribution": "klankbeeld",
      "attributionText": "\"Static Noise\" by klankbeeld (Freesound.org) - CC BY 4.0",
      "tags": ["static", "noise", "focus", "concentration"],
      "featured": false
    },
    {
      "id": "thunder_rain_turku",
      "title": "Thunder Rain Turku",
      "category": "rain",
      "duration": 2619,
      "description": "Thunder and rain recorded in Turku",
      "file": "https://github.com/aymen-igri/DFCraft_sounds_library/releases/download/v1.0.0/thunder_rain_turku.mp3",
      "coverImage": null,
      "thumbnail": null,
      "source": null,
      "sourceUrl": null,
      "license": "Unknown",
      "licenseUrl": null,
      "author": null,
      "attribution": null,
      "tags": ["thunder", "rain", "turku", "storm"],
      "featured": false
    },
    {
      "id": "thunderstorm-83988",
      "title": "Thunderstorm with Heavy Rain",
      "category": "rain",
      "duration": 931,
      "description": "Moderate distant thunderstorm with heavy rain",
      "file": "https://github.com/aymen-igri/DFCraft_sounds_library/releases/download/v1.0.0/thunderstorm-83988.mp3",
      "coverImage": "https://raw.githubusercontent.com/aymen-igri/DFCraft_sounds_library/main/Images/Rain/thunderstorm-83988.jpg",
      "thumbnail": "https://raw.githubusercontent.com/aymen-igri/DFCraft_sounds_library/main/Images/Rain/thunderstorm-83988.jpg",
      "source": "Freesound",
      "sourceUrl": "https://freesound.org/people/crosbychris/sounds/83988/",
      "license": "CC BY 4.0",
      "licenseUrl": "https://creativecommons.org/licenses/by/4.0/",
      "author": "crosbychris",
      "attribution": "crosbychris",
      "attributionText": "\"Thunderstorm with Heavy Rain\" by crosbychris (Freesound.org) - CC BY 4.0",
      "tags": ["thunder", "storm", "rain", "intense"],
      "featured": true
    },
    {
      "id": "birds-around-birdfeeding",
      "title": "Birds Around Birdfeeding",
      "category": "nature",
      "duration": 2650,
      "description": "Birds chirping around a bird feeding area",
      "file": "https://github.com/aymen-igri/DFCraft_sounds_library/releases/download/v1.0.0/birds-around-birdfeeding.mp3",
      "coverImage": null,
      "thumbnail": null,
      "source": null,
      "sourceUrl": null,
      "license": "Unknown",
      "licenseUrl": null,
      "author": null,
      "attribution": null,
      "tags": ["birds", "birdfeeding", "nature", "ambient"],
      "featured": false
    },
    {
      "id": "decatur-georgia",
      "title": "Decatur Georgia",
      "category": "nature",
      "duration": 1925,
      "description": "ATLMorning - ambient outdoor recording",
      "file": "https://github.com/aymen-igri/DFCraft_sounds_library/releases/download/v1.0.0/decatur-georgia.mp3",
      "coverImage": null,
      "thumbnail": null,
      "source": null,
      "sourceUrl": null,
      "license": "Unknown",
      "licenseUrl": null,
      "author": null,
      "attribution": null,
      "tags": ["decatur", "georgia", "morning", "ambient"],
      "featured": false
    },
    {
      "id": "forest-512341",
      "title": "Forest Ambience",
      "category": "nature",
      "duration": 1968,
      "description": "Peaceful forest with birds and wind",
      "file": "https://github.com/aymen-igri/DFCraft_sounds_library/releases/download/v1.0.0/forest-512341.mp3",
      "coverImage": "https://raw.githubusercontent.com/aymen-igri/DFCraft_sounds_library/main/Images/Nature%20&%20Forest/forest-512341.jpg",
      "thumbnail": "https://raw.githubusercontent.com/aymen-igri/DFCraft_sounds_library/main/Images/Nature%20&%20Forest/forest-512341.jpg",
      "source": "Freesound",
      "sourceUrl": "https://freesound.org/people/klankbeeld/sounds/512341/",
      "license": "CC BY 4.0",
      "licenseUrl": "https://creativecommons.org/licenses/by/4.0/",
      "author": "klankbeeld",
      "attribution": "klankbeeld",
      "attributionText": "\"Forest Ambience\" by klankbeeld (Freesound.org) - CC BY 4.0",
      "tags": ["forest", "birds", "nature", "peaceful"],
      "featured": true
    },
    {
      "id": "forest-animals-704437",
      "title": "Forest Animals",
      "category": "nature",
      "duration": 3615,
      "description": "Forest ambience with animal sounds",
      "file": "https://github.com/aymen-igri/DFCraft_sounds_library/releases/download/v1.0.0/forest-animals-704437.mp3",
      "coverImage": null,
      "thumbnail": null,
      "source": null,
      "sourceUrl": null,
      "license": "Unknown",
      "licenseUrl": null,
      "author": null,
      "attribution": null,
      "tags": ["forest", "animals", "nature", "wildlife"],
      "featured": false
    },
    {
      "id": "morning-cicada-and-bird-chorus",
      "title": "Morning Cicada and Bird Chorus",
      "category": "nature",
      "duration": 1538,
      "description": "Early morning chorus of cicadas and birds",
      "file": "https://github.com/aymen-igri/DFCraft_sounds_library/releases/download/v1.0.0/morning-cicada-and-bird-chorus.mp3",
      "coverImage": null,
      "thumbnail": null,
      "source": null,
      "sourceUrl": null,
      "license": "Unknown",
      "licenseUrl": null,
      "author": null,
      "attribution": null,
      "tags": ["morning", "cicada", "birds", "chorus"],
      "featured": false
    },
    {
      "id": "ocean-waves-688988",
      "title": "Ocean Waves",
      "category": "nature",
      "duration": 4944,
      "description": "Calming ocean waves on the beach",
      "file": "https://github.com/aymen-igri/DFCraft_sounds_library/releases/download/v1.0.0/ocean-waves-688988.mp3",
      "coverImage": "https://raw.githubusercontent.com/aymen-igri/DFCraft_sounds_library/main/Images/Nature%20&%20Forest/ocean-waves-688988.jpg",
      "thumbnail": "https://raw.githubusercontent.com/aymen-igri/DFCraft_sounds_library/main/Images/Nature%20&%20Forest/ocean-waves-688988.jpg",
      "source": "Freesound",
      "sourceUrl": "https://freesound.org/people/Ambient-X/sounds/688988/",
      "license": "CC0",
      "licenseUrl": "https://creativecommons.org/publicdomain/zero/1.0/",
      "author": "Ambient-X",
      "attribution": null,
      "tags": ["ocean", "waves", "beach", "calming"],
      "featured": true
    },
    {
      "id": "pink-noise-512341",
      "title": "Pink Noise",
      "category": "nature",
      "duration": 1968,
      "description": "Balanced pink noise for focus",
      "file": "https://github.com/aymen-igri/DFCraft_sounds_library/releases/download/v1.0.0/pink-noise-512341.mp3",
      "coverImage": null,
      "thumbnail": null,
      "source": "Freesound",
      "sourceUrl": "https://freesound.org/people/klankbeeld/sounds/512341/",
      "license": "CC BY 4.0",
      "licenseUrl": "https://creativecommons.org/licenses/by/4.0/",
      "author": "klankbeeld",
      "attribution": "klankbeeld",
      "attributionText": "\"Pink Noise\" by klankbeeld (Freesound.org) - CC BY 4.0",
      "tags": ["pink-noise", "focus", "balanced", "study"],
      "featured": false
    },
    {
      "id": "rouvenac-chemin",
      "title": "Rouvenac Chemin",
      "category": "nature",
      "duration": 15712,
      "description": "Extended outdoor ambience from Rouvenac",
      "file": "https://github.com/aymen-igri/DFCraft_sounds_library/releases/download/v1.0.0/rouvenac-chemin.mp3",
      "coverImage": null,
      "thumbnail": null,
      "source": null,
      "sourceUrl": null,
      "license": "Unknown",
      "licenseUrl": null,
      "author": null,
      "attribution": null,
      "tags": ["rouvenac", "chemin", "nature", "long"],
      "featured": false
    },
    {
      "id": "sterlings",
      "title": "Sterlings",
      "category": "nature",
      "duration": 2404,
      "description": "Sterlings nature ambience",
      "file": "https://github.com/aymen-igri/DFCraft_sounds_library/releases/download/v1.0.0/sterlings.mp3",
      "coverImage": null,
      "thumbnail": null,
      "source": null,
      "sourceUrl": null,
      "license": "Unknown",
      "licenseUrl": null,
      "author": null,
      "attribution": null,
      "tags": ["sterlings", "nature", "ambient"],
      "featured": false
    },
    {
      "id": "summer-forest-267644",
      "title": "Summer Forest",
      "category": "nature",
      "duration": 6785,
      "description": "Vibrant summer forest ambience",
      "file": "https://github.com/aymen-igri/DFCraft_sounds_library/releases/download/v1.0.0/summer-forest-267644.mp3",
      "coverImage": "https://raw.githubusercontent.com/aymen-igri/DFCraft_sounds_library/main/Images/Nature%20&%20Forest/summer-forest-267644.jpg",
      "thumbnail": "https://raw.githubusercontent.com/aymen-igri/DFCraft_sounds_library/main/Images/Nature%20&%20Forest/summer-forest-267644.jpg",
      "source": "Freesound",
      "sourceUrl": "https://freesound.org/people/klankbeeld/sounds/267644/",
      "license": "CC BY 4.0",
      "licenseUrl": "https://creativecommons.org/licenses/by/4.0/",
      "author": "klankbeeld",
      "attribution": "klankbeeld",
      "attributionText": "\"Summer Forest\" by klankbeeld (Freesound.org) - CC BY 4.0",
      "tags": ["forest", "summer", "birds", "nature"],
      "featured": false
    },
    {
      "id": "ambient-fan-bass-boost",
      "title": "Ambient Fan Bass Boost",
      "category": "white-noise",
      "duration": 1801,
      "description": "Ambient fan sound with bass boost",
      "file": "https://github.com/aymen-igri/DFCraft_sounds_library/releases/download/v1.0.0/ambient-fan-bass-boost.mp3",
      "coverImage": null,
      "thumbnail": null,
      "source": null,
      "sourceUrl": null,
      "license": "Unknown",
      "licenseUrl": null,
      "author": null,
      "attribution": null,
      "tags": ["ambient", "fan", "bass", "noise"],
      "featured": false
    },
    {
      "id": "bigwave-to-shallow",
      "title": "Bigwave To Shallow",
      "category": "white-noise",
      "duration": 3600,
      "description": "Big wave transitioning to shallow water",
      "file": "https://github.com/aymen-igri/DFCraft_sounds_library/releases/download/v1.0.0/bigwave-to-shallow.mp3",
      "coverImage": null,
      "thumbnail": null,
      "source": null,
      "sourceUrl": null,
      "license": "Unknown",
      "licenseUrl": null,
      "author": "Hear No Elvis",
      "attribution": null,
      "tags": ["wave", "shallow", "water", "ambient"],
      "featured": false
    },
    {
      "id": "brown-noise-117661",
      "title": "Brown Noise",
      "category": "white-noise",
      "duration": 1098,
      "description": "Deep brown noise for sleep and relaxation",
      "file": "https://github.com/aymen-igri/DFCraft_sounds_library/releases/download/v1.0.0/brown-noise-117661.mp3",
      "coverImage": "https://raw.githubusercontent.com/aymen-igri/DFCraft_sounds_library/main/Images/White%20noise/brown-noise-117661.jpg",
      "thumbnail": "https://raw.githubusercontent.com/aymen-igri/DFCraft_sounds_library/main/Images/White%20noise/brown-noise-117661.jpg",
      "source": "Freesound",
      "sourceUrl": "https://freesound.org/people/BugInTheSYS/sounds/117661/",
      "license": "CC0",
      "licenseUrl": "https://creativecommons.org/publicdomain/zero/1.0/",
      "author": "BugInTheSYS",
      "attribution": null,
      "tags": ["brown-noise", "sleep", "deep", "calming"],
      "featured": false
    },
    {
      "id": "crashing-ocean-waves",
      "title": "Crashing Ocean Waves",
      "category": "white-noise",
      "duration": 10754,
      "description": "Beach Waves Daylight - crashing ocean waves",
      "file": "https://github.com/aymen-igri/DFCraft_sounds_library/releases/download/v1.0.0/crashing-ocean-waves.mp3",
      "coverImage": null,
      "thumbnail": null,
      "source": null,
      "sourceUrl": null,
      "license": "Unknown",
      "licenseUrl": null,
      "author": null,
      "attribution": null,
      "tags": ["ocean", "waves", "crashing", "beach"],
      "featured": false
    },
    {
      "id": "dry-cleaner",
      "title": "Dry Cleaner",
      "category": "white-noise",
      "duration": 4699,
      "description": "Dry cleaner ambient machine noise",
      "file": "https://github.com/aymen-igri/DFCraft_sounds_library/releases/download/v1.0.0/dry-cleaner.mp3",
      "coverImage": null,
      "thumbnail": null,
      "source": null,
      "sourceUrl": null,
      "license": "Unknown",
      "licenseUrl": null,
      "author": null,
      "attribution": null,
      "tags": ["dry-cleaner", "ambient", "indoor", "noise"],
      "featured": false
    },
    {
      "id": "relaxing-soft-noise",
      "title": "Relaxing Soft Noise",
      "category": "white-noise",
      "duration": 4439,
      "description": "74 Minutes of Relaxing Soft Noise",
      "file": "https://github.com/aymen-igri/DFCraft_sounds_library/releases/download/v1.0.0/relaxing-soft-noise.mp3",
      "coverImage": null,
      "thumbnail": null,
      "source": null,
      "sourceUrl": null,
      "license": "Unknown",
      "licenseUrl": null,
      "author": "The Noise Guru",
      "attribution": null,
      "tags": ["relaxing", "soft", "noise", "focus"],
      "featured": false
    },
    {
      "id": "roomtone-emptymall-indoors",
      "title": "Roomtone Empty Mall Indoors",
      "category": "white-noise",
      "duration": 2106,
      "description": "Room-tone of a large empty indoor shopping mall",
      "file": "https://github.com/aymen-igri/DFCraft_sounds_library/releases/download/v1.0.0/roomtone-emptymall-indoors.mp3",
      "coverImage": null,
      "thumbnail": null,
      "source": null,
      "sourceUrl": null,
      "license": "Unknown",
      "licenseUrl": null,
      "author": "klankbeeld",
      "attribution": null,
      "tags": ["roomtone", "empty", "mall", "indoor"],
      "featured": false
    },
    {
      "id": "ultra-soft-noise",
      "title": "Ultra Soft Noise",
      "category": "white-noise",
      "duration": 3606,
      "description": "60 Minutes of Ultra-Relaxing Soft Noise",
      "file": "https://github.com/aymen-igri/DFCraft_sounds_library/releases/download/v1.0.0/ultra-soft-noise.mp3",
      "coverImage": null,
      "thumbnail": null,
      "source": null,
      "sourceUrl": null,
      "license": "Unknown",
      "licenseUrl": null,
      "author": "The Noise Guru",
      "attribution": null,
      "tags": ["ultra-soft", "noise", "relaxing", "focus"],
      "featured": false
    },
    {
      "id": "white-noise-403326",
      "title": "White Noise",
      "category": "white-noise",
      "duration": 8340,
      "description": "Pure white noise for concentration",
      "file": "https://github.com/aymen-igri/DFCraft_sounds_library/releases/download/v1.0.0/white-noise-403326.mp3",
      "coverImage": "https://raw.githubusercontent.com/aymen-igri/DFCraft_sounds_library/main/Images/White%20noise/white-noise-403326.jpg",
      "thumbnail": "https://raw.githubusercontent.com/aymen-igri/DFCraft_sounds_library/main/Images/White%20noise/white-noise-403326.jpg",
      "source": "Freesound",
      "sourceUrl": "https://freesound.org/people/assett1/sounds/403326/",
      "license": "CC0",
      "licenseUrl": "https://creativecommons.org/publicdomain/zero/1.0/",
      "author": "assett1",
      "attribution": null,
      "tags": ["white-noise", "focus", "concentration", "study"],
      "featured": true
    },
    {
      "id": "white-noise-from-chroma-doza",
      "title": "White Noise From Chroma Doze",
      "category": "white-noise",
      "duration": 3735,
      "description": "Low White Noise generated with Chroma Doze",
      "file": "https://github.com/aymen-igri/DFCraft_sounds_library/releases/download/v1.0.0/white-noise-from-chroma-doza.mp3",
      "coverImage": null,
      "thumbnail": null,
      "source": null,
      "sourceUrl": null,
      "license": "CC0",
      "licenseUrl": "https://creativecommons.org/publicdomain/zero/1.0/",
      "author": "Joseph Morris",
      "attribution": null,
      "tags": ["white-noise", "chroma-doze", "low", "generated"],
      "featured": false
    },
    {
      "id": "cafe-788774",
      "title": "Cafe Ambience",
      "category": "cafe-indoor",
      "duration": 2088,
      "description": "Cozy cafe atmosphere with chatter and coffee sounds",
      "file": "https://github.com/aymen-igri/DFCraft_sounds_library/releases/download/v1.0.0/cafe-788774.mp3",
      "coverImage": "https://raw.githubusercontent.com/aymen-igri/DFCraft_sounds_library/main/Images/Caf%C3%A9%20&%20Indor/cafe-788774.jpg",
      "thumbnail": "https://raw.githubusercontent.com/aymen-igri/DFCraft_sounds_library/main/Images/Caf%C3%A9%20&%20Indor/cafe-788774.jpg",
      "source": "Freesound",
      "sourceUrl": "https://freesound.org/people/klankbeeld/sounds/788774/",
      "license": "CC BY 4.0",
      "licenseUrl": "https://creativecommons.org/licenses/by/4.0/",
      "author": "klankbeeld",
      "attribution": "klankbeeld",
      "attributionText": "\"Cafe Ambience\" by klankbeeld (Freesound.org) - CC BY 4.0",
      "tags": ["cafe", "coffee", "indoor", "cozy"],
      "featured": true
    },
    {
      "id": "cafe-ambience-in-seoul",
      "title": "Cafe Ambience in Seoul",
      "category": "cafe-indoor",
      "duration": 3398,
      "description": "Cafe atmosphere recorded in Seoul",
      "file": "https://github.com/aymen-igri/DFCraft_sounds_library/releases/download/v1.0.0/cafe-ambience-in-seoul.mp3",
      "coverImage": null,
      "thumbnail": null,
      "source": null,
      "sourceUrl": null,
      "license": "Unknown",
      "licenseUrl": null,
      "author": null,
      "attribution": null,
      "tags": ["cafe", "ambience", "seoul", "indoor"],
      "featured": false
    },
    {
      "id": "coffee-shop-647551",
      "title": "Coffee Shop",
      "category": "cafe-indoor",
      "duration": 3432,
      "description": "Busy coffee shop ambience",
      "file": "https://github.com/aymen-igri/DFCraft_sounds_library/releases/download/v1.0.0/coffee-shop-647551.mp3",
      "coverImage": "https://raw.githubusercontent.com/aymen-igri/DFCraft_sounds_library/main/Images/Caf%C3%A9%20&%20Indor/coffee-shop-647551.jpg",
      "thumbnail": "https://raw.githubusercontent.com/aymen-igri/DFCraft_sounds_library/main/Images/Caf%C3%A9%20&%20Indor/coffee-shop-647551.jpg",
      "source": "Freesound",
      "sourceUrl": "https://freesound.org/people/kevp888/sounds/647551/",
      "license": "CC0",
      "licenseUrl": "https://creativecommons.org/publicdomain/zero/1.0/",
      "author": "kevp888",
      "attribution": null,
      "tags": ["coffee", "shop", "busy", "indoor"],
      "featured": false
    },
    {
      "id": "coffee-shop",
      "title": "Coffee Shop",
      "category": "cafe-indoor",
      "duration": 1689,
      "description": "Coffee shop ambiance",
      "file": "https://github.com/aymen-igri/DFCraft_sounds_library/releases/download/v1.0.0/coffee-shop.mp3",
      "coverImage": null,
      "thumbnail": null,
      "source": null,
      "sourceUrl": null,
      "license": "Unknown",
      "licenseUrl": null,
      "author": null,
      "attribution": null,
      "tags": ["coffee", "shop", "ambiance", "indoor"],
      "featured": false
    },
    {
      "id": "french-coffee-ambience",
      "title": "French Coffee Ambience",
      "category": "cafe-indoor",
      "duration": 2225,
      "description": "French coffee shop ambience",
      "file": "https://github.com/aymen-igri/DFCraft_sounds_library/releases/download/v1.0.0/french-coffee-ambience.mp3",
      "coverImage": null,
      "thumbnail": null,
      "source": null,
      "sourceUrl": null,
      "license": "Unknown",
      "licenseUrl": null,
      "author": null,
      "attribution": null,
      "tags": ["french", "coffee", "ambience", "cafe"],
      "featured": false
    },
    {
      "id": "restaurant-394329",
      "title": "Restaurant Ambience",
      "category": "cafe-indoor",
      "duration": 348,
      "description": "Warm restaurant background atmosphere",
      "file": "https://github.com/aymen-igri/DFCraft_sounds_library/releases/download/v1.0.0/restaurant-394329.mp3",
      "coverImage": "https://raw.githubusercontent.com/aymen-igri/DFCraft_sounds_library/main/Images/Caf%C3%A9%20&%20Indor/restaurant-394329.jpg",
      "thumbnail": "https://raw.githubusercontent.com/aymen-igri/DFCraft_sounds_library/main/Images/Caf%C3%A9%20&%20Indor/restaurant-394329.jpg",
      "source": "Freesound",
      "sourceUrl": "https://freesound.org/people/FreeToUseSounds/sounds/394329/",
      "license": "CC0",
      "licenseUrl": "https://creativecommons.org/publicdomain/zero/1.0/",
      "author": "FreeToUseSounds",
      "attribution": null,
      "tags": ["restaurant", "dining", "indoor", "warm"],
      "featured": false
    },
    {
      "id": "swedish-library",
      "title": "Swedish Library",
      "category": "cafe-indoor",
      "duration": 1819,
      "description": "Quiet library ambience from Sweden",
      "file": "https://github.com/aymen-igri/DFCraft_sounds_library/releases/download/v1.0.0/swedish-library.mp3",
      "coverImage": null,
      "thumbnail": null,
      "source": null,
      "sourceUrl": null,
      "license": "Unknown",
      "licenseUrl": null,
      "author": null,
      "attribution": null,
      "tags": ["library", "swedish", "indoor", "quiet"],
      "featured": false
    }
  ],

  "stats": {
    "totalSounds": 37,
    "totalCategories": 4,
    "totalDuration": 152570,
    "lastUpdated": "2026-06-26T12:00:00Z"
  }
}
